holly_py/__init__.py
holly_py/core.py
holly_py-0.1.0.dist-info/licenses/LICENSE
holly_py-0.1.0.dist-info/METADATA
holly_py-0.1.0.dist-info/WHEEL
holly_py-0.1.0.dist-info/top_level.txt
holly_py-0.1.0.dist-info/RECORD
